hiku-0.7.6.dist-info/METADATA
hiku-0.7.6.dist-info/WHEEL
hiku-0.7.6.dist-info/entry_points.txt
hiku-0.7.6.dist-info/licenses/LICENSE.txt
hiku/__init__.py
hiku/builder.py
hiku/cache.py
hiku/compat.py
hiku/context.py
hiku/denormalize/__init__.py
hiku/denormalize/base.py
hiku/denormalize/graphql.py
hiku/directives/__init__.py
hiku/endpoint/__init__.py
hiku/endpoint/graphql.py
hiku/engine.py
hiku/enum.py
hiku/error.py
hiku/executors/__init__.py
hiku/executors/asyncio.py
hiku/executors/base.py
hiku/executors/queue.py
hiku/executors/sync.py
hiku/executors/threads.py
hiku/export/__init__.py
hiku/export/graphql.py
hiku/expr/__init__.py
hiku/expr/checker.py
hiku/expr/compiler.py
hiku/expr/core.py
hiku/expr/nodes.py
hiku/expr/refs.py
hiku/extensions/__init__.py
hiku/extensions/base_extension.py
hiku/extensions/base_validator.py
hiku/extensions/context.py
hiku/extensions/prometheus.py
hiku/extensions/query_depth_validator.py
hiku/extensions/query_parse_cache.py
hiku/extensions/query_validation_cache.py
hiku/extensions/sentry.py
hiku/federation/__init__.py
hiku/federation/directive.py
hiku/federation/graph.py
hiku/federation/introspection.py
hiku/federation/scalars.py
hiku/federation/schema.py
hiku/federation/sdl.py
hiku/federation/utils.py
hiku/federation/version.py
hiku/graph.py
hiku/introspection/__init__.py
hiku/introspection/graphql.py
hiku/introspection/types.py
hiku/merge.py
hiku/operation.py
hiku/py.typed
hiku/query.py
hiku/readers/__init__.py
hiku/readers/graphql.py
hiku/result.py
hiku/scalar.py
hiku/schema.py
hiku/sources/__init__.py
hiku/sources/aiopg.py
hiku/sources/graph.py
hiku/sources/sqlalchemy.py
hiku/sources/sqlalchemy_async.py
hiku/telemetry/__init__.py
hiku/telemetry/prometheus.py
hiku/types.py
hiku/utils/__init__.py
hiku/utils/const.py
hiku/utils/immutable.py
hiku/utils/serialize.py
hiku/utils/typing.py
hiku/validate/__init__.py
hiku/validate/errors.py
hiku/validate/graph.py
hiku/validate/query.py
hiku-0.7.6.dist-info/RECORD
