Metadata-Version: 2.1
Name: hiku
Version: 0.7.6
Summary: Library to implement Graph APIs
Author-Email: Vladimir Magamedov <vladimir@magamedov.com>, Maksym Kindritskyi <kindritskiy.m@gmail.com>
License: BSD-3-Clause
Classifier: Development Status :: 5 - Production/Stable
Classifier: Intended Audience :: Developers
Classifier: License :: OSI Approved :: BSD License
Classifier: Operating System :: OS Independent
Classifier: Programming Language :: Python
Classifier: Programming Language :: Python :: 3.8
Classifier: Programming Language :: Python :: 3.9
Classifier: Programming Language :: Python :: 3.10
Classifier: Programming Language :: Python :: 3.11
Classifier: Programming Language :: Python :: 3.12
Classifier: Programming Language :: Python :: 3 :: Only
Classifier: Topic :: Software Development :: Libraries :: Python Modules
Project-URL: Documentation, https://hiku.readthedocs.io/en/latest/
Project-URL: Repository, https://github.com/evo-company/hiku
Project-URL: Homepage, https://github.com/evo-company/hiku
Requires-Python: >=3.8
